Workbook

Sheet Glossary
A1: Cinema | B1: Specific location of the cinema
A2: Weekly Customers | B2: Average weekly customers watching a movie
A3: Weekly Popcorn Sales | B3: Average number of popcorn containers (in units) sold weekly
A4: Weekly Food Sales | B4: Average number of hamburgers, wings, and hot dogs (in units) sold weekly
A5: Weekly Soda Sales | B5: Average number of sodas (in units) sold weekly
A6: Ocupación de Sala | B6: Total seats available divided by the number of customers who arrived
A7: FTEs | B7: Number of employees
A8: Waiting time | B8: Average time a customer waits in line to buy a ticket and watch the movie (expressed in minutes)
A9: CSAT | B9: Customer satisfaction, on a scale of 1 to 10
A10: Profits per ticket | B10: Profit in dollars per ticket
A11: Profits per popcorn | B11: Profit in dollars per popcorn container
A12: Profits per soda | B12: Profit in dollars per soda
A13: Profits per Food | B13: Profit in dollars per food dish

Sheet Original Data
A1: Month | B1: Weekly Customers | C1: Weekly Popcorn Sales | D1: Weekly Soda Sales | E1: Weekly Food Sales | F1: Profit per Ticket | G1: Profit per Popcorn | H1: Profit per Soda | I1: Profit per Food | J1: Room Occupancy | K1: FTEs | L1: Waiting Time | M1: CSAT | N1: Main Detractors
A2: 1 | B2: 854 | C2: 265 | D2: 280 | E2: 135 | F2: 5 | G2: 4.25 | H2: 2.5 | I2: 6 | J2: 0.49 | K2: 15 | L2: 12 | M2: 6 | N2: Cleanliness of the room
A3: 2 | B3: 1138 | C3: 1001 | D3: 1033 | E3: 229 | F3: 5 | G3: 4.25 | H3: 2.5 | I3: 6 | J3: 0.65 | K3: 15 | L3: 21 | M3: 7 | N3: Waiting time
A4: 3 | B4: 471 | C4: 414 | D4: 476 | E4: 91 | F4: 5 | G4: 4.25 | H4: 2.5 | I4: 6 | J4: 0.27 | K4: 15 | L4: 8 | M4: 1 | N4: Food quality
A5: 4 | B5: 1014 | C5: 172 | D5: 187 | E5: 102 | F5: 5 | G5: 4.25 | H5: 2.5 | I5: 6 | J5: 0.58 | K5: 15 | L5: 21 | M5: 3 | N5: Cleanliness of the room
A6: 5 | B6: 959 | C6: 777 | D6: 865 | E6: 108 | F6: 5 | G6: 4.25 | H6: 2.5 | I6: 6 | J6: 0.55 | K6: 15 | L6: 25 | M6: 8 | N6: Waiting time
A7: 6 | B7: 1429 | C7: 815 | D7: 853 | E7: 246 | F7: 5 | G7: 4.25 | H7: 2.5 | I7: 6 | J7: 0.82 | K7: 15 | L7: 10 | M7: 2 | N7: Food quality
A8: 7 | B8: 972 | C8: 146 | D8: 147 | E8: 192 | F8: 5 | G8: 4.25 | H8: 2.5 | I8: 6 | J8: 0.56 | K8: 15 | L8: 15 | M8: 2 | N8: Smell in the room
A9: 8 | B9: 861 | C9: 499 | D9: 505 | E9: 192 | F9: 5 | G9: 4.25 | H9: 2.5 | I9: 6 | J9: 0.49 | K9: 15 | L9: 8 | M9: 3 | N9: Food quality
A10: 9 | B10: 308 | C10: 206 | D10: 210 | E10: 39 | F10: 5 | G10: 4.25 | H10: 2.5 | I10: 6 | J10: 0.18 | K10: 15 | L10: 6 | M10: 6 | N10: Cleanliness of the room
A11: 10 | B11: 1199 | C11: 983 | D11: 1037 | E11: 161 | F11: 5 | G11: 4.25 | H11: 2.5 | I11: 6 | J11: 0.69 | K11: 15 | L11: 18 | M11: 7 | N11: Waiting time
A12: 11 | B12: 1011 | C12: 354 | D12: 393 | E12: 110 | F12: 5 | G12: 4.25 | H12: 2.5 | I12: 6 | J12: 0.58 | K12: 15 | L12: 5 | M12: 3 | N12: Food quality
A13: 12 | B13: 1608 | C13: 933 | D13: 1005 | E13: 229 | F13: 5 | G13: 4.25 | H13: 2.5 | I13: 6 | J13: 0.92 | K13: 15 | L13: 7 | M13: 4 | N13: Cleanliness of the room

Sheet Monthly Profit & Refined Data
C2: Cinema's Item Profits & Operational Constants. | I2: Deriving Monthly Multiplier
I5: Days a Year | J5: 365
I6: Weeks a Year | J6: =J5/7 -> 52.142857 | K6: **7 days a week**
C7: Profit per Ticket | D7: Profit per Popcorn | E7: Profit per Soda | F7: Profit per Food | G7: FTEs | I7: Months a Year | J7: =J6/12 -> 4.3452381 | K7: **12 months a year**
C8: 5 | D8: 4.25 | E8: 2.5 | F8: 6 | G8: 15 | I8: Week to Months Multiplier | J8: =J7 -> 4.3452381
L11: Assumption: Sales meaning indivisual transactions/purchases of product X
L12: Derived from Weekly Cust. | M12: Derived from Weekly Popcorn Sales | N12: Derived from Weekly Soda Sales | O12: Derived from Weekly Food Sales
B13: Month | C13: Monthly Ticket Profit | D13: Monthly Popcorn Profit | E13: Monthly Soda Profit | F13: Monthly Food Profit | G13: Total Month Profit | H13: Waiting Time | I13: CSAT | J13: Main Detractors (Original) | K13: Main Detractors (Derived) | L13: Monthly Customers | M13: Monthly Popcorn Sales | N13: Monthly Soda Sales | O13: Monthly Food Sales
B14: 1 | C14: =$J$8*$C$8*'Original Data'!B2 -> 18554.167 | D14: =$J$8*$D$8*'Original Data'!C2 -> 4893.8244 | E14: =$J$8*$E$8*'Original Data'!D2 -> 3041.6667 | F14: =$J$8*$F$8*'Original Data'!E2 -> 3519.6429 | G14: =SUM(C14:F14) -> 30009.301 | H14: 12 | I14: 6 | J14: Cleanliness of the room | K14: Cinema Hygeine | L14: ='Original Data'!B2*$J$8 -> 3710.8333 | M14: ='Original Data'!C2*$J$8 -> 1151.4881 | N14: ='Original Data'!D2*$J$8 -> 1216.6667 | O14: ='Original Data'!E2*$J$8 -> 586.60714
B15: 2 | C15: =$J$8*$C$8*'Original Data'!B3 -> 24724.405 | D15: =$J$8*$D$8*'Original Data'!C3 -> 18485.729 | E15: =$J$8*$E$8*'Original Data'!D3 -> 11221.577 | F15: =$J$8*$F$8*'Original Data'!E3 -> 5970.3571 | G15: =SUM(C15:F15) -> 60402.068 | H15: 21 | I15: 7 | J15: Waiting time | K15: Waiting time | L15: ='Original Data'!B3*$J$8 -> 4944.881 | M15: ='Original Data'!C3*$J$8 -> 4349.5833 | N15: ='Original Data'!D3*$J$8 -> 4488.631 | O15: ='Original Data'!E3*$J$8 -> 995.05952
B16: 3 | C16: =$J$8*$C$8*'Original Data'!B4 -> 10233.036 | D16: =$J$8*$D$8*'Original Data'!C4 -> 7645.4464 | E16: =$J$8*$E$8*'Original Data'!D4 -> 5170.8333 | F16: =$J$8*$F$8*'Original Data'!E4 -> 2372.5 | G16: =SUM(C16:F16) -> 25421.815 | H16: 8 | I16: 1 | J16: Food quality | K16: Food quality | L16: ='Original Data'!B4*$J$8 -> 2046.6071 | M16: ='Original Data'!C4*$J$8 -> 1798.9286 | N16: ='Original Data'!D4*$J$8 -> 2068.3333 | O16: ='Original Data'!E4*$J$8 -> 395.41667
B17: 4 | C17: =$J$8*$C$8*'Original Data'!B5 -> 22030.357 | D17: =$J$8*$D$8*'Original Data'!C5 -> 3176.369 | E17: =$J$8*$E$8*'Original Data'!D5 -> 2031.3988 | F17: =$J$8*$F$8*'Original Data'!E5 -> 2659.2857 | G17: =SUM(C17:F17) -> 29897.411 | H17: 21 | I17: 3 | J17: Cleanliness of the room | K17: Cinema Hygeine | L17: ='Original Data'!B5*$J$8 -> 4406.0714 | M17: ='Original Data'!C5*$J$8 -> 747.38095 | N17: ='Original Data'!D5*$J$8 -> 812.55952 | O17: ='Original Data'!E5*$J$8 -> 443.21429
B18: 5 | C18: =$J$8*$C$8*'Original Data'!B6 -> 20835.417 | D18: =$J$8*$D$8*'Original Data'!C6 -> 14349.063 | E18: =$J$8*$E$8*'Original Data'!D6 -> 9396.5774 | F18: =$J$8*$F$8*'Original Data'!E6 -> 2815.7143 | G18: =SUM(C18:F18) -> 47396.771 | H18: 25 | I18: 8 | J18: Waiting time | K18: Waiting time | L18: ='Original Data'!B6*$J$8 -> 4167.0833 | M18: ='Original Data'!C6*$J$8 -> 3376.25 | N18: ='Original Data'!D6*$J$8 -> 3758.631 | O18: ='Original Data'!E6*$J$8 -> 469.28571
B19: 6 | C19: =$J$8*$C$8*'Original Data'!B7 -> 31046.726 | D19: =$J$8*$D$8*'Original Data'!C7 -> 15050.818 | E19: =$J$8*$E$8*'Original Data'!D7 -> 9266.2202 | F19: =$J$8*$F$8*'Original Data'!E7 -> 6413.5714 | G19: =SUM(C19:F19) -> 61777.336 | H19: 10 | I19: 2 | J19: Food quality | K19: Food quality | L19: ='Original Data'!B7*$J$8 -> 6209.3452 | M19: ='Original Data'!C7*$J$8 -> 3541.369 | N19: ='Original Data'!D7*$J$8 -> 3706.4881 | O19: ='Original Data'!E7*$J$8 -> 1068.9286
B20: 7 | C20: =$J$8*$C$8*'Original Data'!B8 -> 21117.857 | D20: =$J$8*$D$8*'Original Data'!C8 -> 2696.2202 | E20: =$J$8*$E$8*'Original Data'!D8 -> 1596.875 | F20: =$J$8*$F$8*'Original Data'!E8 -> 5005.7143 | G20: =SUM(C20:F20) -> 30416.667 | H20: 15 | I20: 2 | J20: Smell in the room | K20: Cinema Hygeine | L20: ='Original Data'!B8*$J$8 -> 4223.5714 | M20: ='Original Data'!C8*$J$8 -> 634.40476 | N20: ='Original Data'!D8*$J$8 -> 638.75 | O20: ='Original Data'!E8*$J$8 -> 834.28571
B21: 8 | C21: =$J$8*$C$8*'Original Data'!B9 -> 18706.25 | D21: =$J$8*$D$8*'Original Data'!C9 -> 9215.1637 | E21: =$J$8*$E$8*'Original Data'!D9 -> 5485.8631 | F21: =$J$8*$F$8*'Original Data'!E9 -> 5005.7143 | G21: =SUM(C21:F21) -> 38412.991 | H21: 8 | I21: 3 | J21: Food quality | K21: Food quality | L21: ='Original Data'!B9*$J$8 -> 3741.25 | M21: ='Original Data'!C9*$J$8 -> 2168.2738 | N21: ='Original Data'!D9*$J$8 -> 2194.3452 | O21: ='Original Data'!E9*$J$8 -> 834.28571
B22: 9 | C22: =$J$8*$C$8*'Original Data'!B10 -> 6691.6667 | D22: =$J$8*$D$8*'Original Data'!C10 -> 3804.256 | E22: =$J$8*$E$8*'Original Data'!D10 -> 2281.25 | F22: =$J$8*$F$8*'Original Data'!E10 -> 1016.7857 | G22: =SUM(C22:F22) -> 13793.958 | H22: 6 | I22: 6 | J22: Cleanliness of the room | K22: Cinema Hygeine | L22: ='Original Data'!B10*$J$8 -> 1338.3333 | M22: ='Original Data'!C10*$J$8 -> 895.11905 | N22: ='Original Data'!D10*$J$8 -> 912.5 | O22: ='Original Data'!E10*$J$8 -> 169.46429
B23: 10 | C23: =$J$8*$C$8*'Original Data'!B11 -> 26049.702 | D23: =$J$8*$D$8*'Original Data'!C11 -> 18153.318 | E23: =$J$8*$E$8*'Original Data'!D11 -> 11265.03 | F23: =$J$8*$F$8*'Original Data'!E11 -> 4197.5 | G23: =SUM(C23:F23) -> 59665.551 | H23: 18 | I23: 7 | J23: Waiting time | K23: Waiting time | L23: ='Original Data'!B11*$J$8 -> 5209.9405 | M23: ='Original Data'!C11*$J$8 -> 4271.369 | N23: ='Original Data'!D11*$J$8 -> 4506.0119 | O23: ='Original Data'!E11*$J$8 -> 699.58333
B24: 11 | C24: =$J$8*$C$8*'Original Data'!B12 -> 21965.179 | D24: =$J$8*$D$8*'Original Data'!C12 -> 6537.4107 | E24: =$J$8*$E$8*'Original Data'!D12 -> 4269.1964 | F24: =$J$8*$F$8*'Original Data'!E12 -> 2867.8571 | G24: =SUM(C24:F24) -> 35639.643 | H24: 5 | I24: 3 | J24: Food quality | K24: Food quality | L24: ='Original Data'!B12*$J$8 -> 4393.0357 | M24: ='Original Data'!C12*$J$8 -> 1538.2143 | N24: ='Original Data'!D12*$J$8 -> 1707.6786 | O24: ='Original Data'!E12*$J$8 -> 477.97619
B25: 12 | C25: =$J$8*$C$8*'Original Data'!B13 -> 34935.714 | D25: =$J$8*$D$8*'Original Data'!C13 -> 17229.955 | E25: =$J$8*$E$8*'Original Data'!D13 -> 10917.411 | F25: =$J$8*$F$8*'Original Data'!E13 -> 5970.3571 | G25: =SUM(C25:F25) -> 69053.438 | H25: 7 | I25: 4 | J25: Cleanliness of the room | K25: Cinema Hygeine | L25: ='Original Data'!B13*$J$8 -> 6987.1429 | M25: ='Original Data'!C13*$J$8 -> 4054.1071 | N25: ='Original Data'!D13*$J$8 -> 4366.9643 | O25: ='Original Data'!E13*$J$8 -> 995.05952
B26: SUM | C26: =SUBTOTAL(109,Table3[Monthly Ticket Profit]) -> 256890.48 | D26: =SUBTOTAL(109,Table3[Monthly Popcorn Profit]) -> 121237.57 | E26: =SUBTOTAL(109,Table3[Monthly Soda Profit]) -> 75943.899 | F26: =SUM(Table3[Monthly Food Profit]) -> 47815 | G26: =SUM(Table3[Total Month Profit]) -> 501886.95 | L26: =SUM(Table3[Monthly Customers]) -> 51378.095 | M26: =SUM(Table3[Monthly Popcorn Sales]) -> 28526.488 | N26: =SUM(Table3[Monthly Soda Sales]) -> 30377.56 | O26: =SUM(Table3[Monthly Food Sales]) -> 7969.1667
F30: Total Yearly Profit | G30: 501886.95
F31: Target Profit Rate | G31: 0.2
F32: Target Profit Number | G32: =Table3[[#Totals],[Total Month Profit]]+(G31*Table3[[#Totals],[Total Month Profit]]) -> 602264.34

Sheet Profit & KPI Analysis
B2: Current Year KPIs
B5: Profit Distribution between F&B and Ticket Sales
B6: Division | C6: Precentage
B7: Ticket | C7: =(Table3[[#Totals],[Monthly Ticket Profit]]/Table3[[#Totals],[Total Month Profit]]) -> 0.51184928
B8: F&B | C8: =SUM(Table3[[#Totals],[Monthly Popcorn Profit]:[Monthly Food Profit]])/Table3[[#Totals],[Total Month Profit]] -> 0.48815072
B10: Total Distribution of Profit per Item Breakdown
B11: Item | C11: Precentage
B12: Ticket | C12: =(Table3[[#Totals],[Monthly Ticket Profit]]/Table3[[#Totals],[Total Month Profit]]) -> 0.51184928
B13: Popcorn | C13: =Table3[[#Totals],[Monthly Popcorn Profit]]/Table3[[#Totals],[Total Month Profit]] -> 0.24156351
B14: Soda | C14: =Table3[[#Totals],[Monthly Soda Profit]]/Table3[[#Totals],[Total Month Profit]] -> 0.15131674 | E14: Identified Issue: Low Purchase Rate of F&B Products Solutions: 1. Create F&B Offers for Cinema Customers 2. Making Food & Items Available for Purchase Standalone 3. Sell & Advertise F&B Items on Food Delivery Apps such as Talabat (Case Study VOX Cinema).
B15: Food | C15: =Table3[[#Totals],[Monthly Food Profit]]/Table3[[#Totals],[Total Month Profit]] -> 0.095270459
B17: Purchase Rate of F&B Items Breakdown by Customer
B18: (Ticket Purchasers and What are they Purchasing in addition)
B19: Item | C19: Precentage
B20: Popcorn | C20: =Table3[[#Totals],[Monthly Popcorn Sales]]/Table3[[#Totals],[Monthly Customers]] -> 0.55522666
B21: Soda | C21: =Table3[[#Totals],[Monthly Soda Sales]]/Table3[[#Totals],[Monthly Customers]] -> 0.59125507
B22: Food | C22: =Table3[[#Totals],[Monthly Food Sales]]/Table3[[#Totals],[Monthly Customers]] -> 0.15510825
B24: CSAT Breakdown
B25: Detractors | C25: Average of CSAT
B26: Cinema Hygeine | C26: 4.2 | E26: Identified Issue: Cinema Hygeine & Food Quality as biggest detractors Solution: Implement Quality Control on both Cinema Hygeine and Food Quality. Customers are more forgiving of wait time than hygeine or food quality
B27: Food quality | C27: 2.25
B28: Waiting time | C28: 7.3333333
B29: CSAT Avg | C29: 4.3333333
B31: Customers Per Employee Ratio Daily
B32: **Employee count is static at 15 all year round**
B33: Months | C33: Customers/Employee Ratio | D33: Daily Cust. | E33: Wait Time
B34: 1 | C34: =('Monthly Profit & Refined Data'!L14/'Monthly Profit & Refined Data'!$G$8)/30 -> 8.2462963 | D34: ='Monthly Profit & Refined Data'!L14/30 -> 123.69444 | E34: ='Monthly Profit & Refined Data'!H14 -> 12
B35: 2 | C35: =('Monthly Profit & Refined Data'!L15/'Monthly Profit & Refined Data'!$G$8)/30 -> 10.988624 | D35: ='Monthly Profit & Refined Data'!L15/30 -> 164.82937 | E35: ='Monthly Profit & Refined Data'!H15 -> 21
B36: 3 | C36: =('Monthly Profit & Refined Data'!L16/'Monthly Profit & Refined Data'!$G$8)/30 -> 4.5480159 | D36: ='Monthly Profit & Refined Data'!L16/30 -> 68.220238 | E36: ='Monthly Profit & Refined Data'!H16 -> 8 | G36: Identified Issue: Static Employee Count & Operational & Training Inefficiency 1. Static employee count year round can result in redundancy if the employees work efficiently. 2. Operational Inefficiency: Month 12 has highest customer count with lowest wait time compared to Month 5 with low customer count with highest wait time Solution: Provide Adequate Training to Employees & Flexible Employee Count to Minimize Costs and use the average as a baseline as a future KPI.
B37: 4 | C37: =('Monthly Profit & Refined Data'!L17/'Monthly Profit & Refined Data'!$G$8)/30 -> 9.7912698 | D37: ='Monthly Profit & Refined Data'!L17/30 -> 146.86905 | E37: ='Monthly Profit & Refined Data'!H17 -> 21
B38: 5 | C38: =('Monthly Profit & Refined Data'!L18/'Monthly Profit & Refined Data'!$G$8)/30 -> 9.2601852 | D38: ='Monthly Profit & Refined Data'!L18/30 -> 138.90278 | E38: ='Monthly Profit & Refined Data'!H18 -> 25
B39: 6 | C39: =('Monthly Profit & Refined Data'!L19/'Monthly Profit & Refined Data'!$G$8)/30 -> 13.798545 | D39: ='Monthly Profit & Refined Data'!L19/30 -> 206.97817 | E39: ='Monthly Profit & Refined Data'!H19 -> 10
B40: 7 | C40: =('Monthly Profit & Refined Data'!L20/'Monthly Profit & Refined Data'!$G$8)/30 -> 9.3857143 | D40: ='Monthly Profit & Refined Data'!L20/30 -> 140.78571 | E40: ='Monthly Profit & Refined Data'!H20 -> 15
B41: 8 | C41: =('Monthly Profit & Refined Data'!L21/'Monthly Profit & Refined Data'!$G$8)/30 -> 8.3138889 | D41: ='Monthly Profit & Refined Data'!L21/30 -> 124.70833 | E41: ='Monthly Profit & Refined Data'!H21 -> 8
B42: 9 | C42: =('Monthly Profit & Refined Data'!L22/'Monthly Profit & Refined Data'!$G$8)/30 -> 2.9740741 | D42: ='Monthly Profit & Refined Data'!L22/30 -> 44.611111 | E42: ='Monthly Profit & Refined Data'!H22 -> 6
B43: 10 | C43: =('Monthly Profit & Refined Data'!L23/'Monthly Profit & Refined Data'!$G$8)/30 -> 11.577646 | D43: ='Monthly Profit & Refined Data'!L23/30 -> 173.66468 | E43: ='Monthly Profit & Refined Data'!H23 -> 18
B44: 11 | C44: =('Monthly Profit & Refined Data'!L24/'Monthly Profit & Refined Data'!$G$8)/30 -> 9.7623016 | D44: ='Monthly Profit & Refined Data'!L24/30 -> 146.43452 | E44: ='Monthly Profit & Refined Data'!H24 -> 5
B45: 12 | C45: =('Monthly Profit & Refined Data'!L25/'Monthly Profit & Refined Data'!$G$8)/30 -> 15.526984 | D45: ='Monthly Profit & Refined Data'!L25/30 -> 232.90476 | E45: ='Monthly Profit & Refined Data'!H25 -> 7
B46: Average | C46: =AVERAGE(C34:C45) -> 9.5144621 | D46: =AVERAGE(D34:D45) -> 142.71693 | E46: =AVERAGE(E34:E45) -> 13

Sheet Reaching Target
B2: Total Yearly Profit | C2: =Table3[[#Totals],[Total Month Profit]] -> 501886.95
B3: Target Profit Rate | C3: 0.2 | E3: The Following Calculations are Based On Static Customer Base: | I3: ='Monthly Profit & Refined Data'!$L$26 -> 51378.095
B4: Target Profit Number | C4: =Table3[[#Totals],[Total Month Profit]]+(C3*Table3[[#Totals],[Total Month Profit]]) -> 602264.34
B5: Total Achieved Number | C5: =SUM(F14:F15,E25,M24,M15) -> 638617.53
B8: 1. Cinema Promo for Most Purchased Items (Soda+Popcorn+Ticket) to Replace Indivisual Sales **Assuming Customers Purchase Only the Combo Pack without Additional Items** | I8: 2. Increase F&B Sales by Hosting Items on Food Delivery Apps for Standalone Purchases **Approximate 25% Increase in Each Item Sales**
C10: Original Combined Profit for Items: | F10: =SUM('Monthly Profit & Refined Data'!$C$8:$E$8) -> 11.75
C11: Discount Rate: | F11: 0.12 | J11: Item | K11: Profit | L11: Expected Additional Sales | M11: Expected Additional Profit
C12: Discounted Profit Amount for Combo | F12: =F10-(F10*F11) -> 10.34 | J12: Profit per Popcorn | K12: 4.25 | L12: =0.25*Table3[[#Totals],[Monthly Popcorn Sales]] -> 7131.622 | M12: =L12*K12 -> 30309.394
C13: Assumed % Purchase Rate for Promo | F13: 0.75 | J13: Profit per Soda | K13: 2.5 | L13: =0.25*Table3[[#Totals],[Monthly Soda Sales]] -> 7594.3899 | M13: =L13*K13 -> 18985.975
C14: Total Estimated Profits: | F14: =F13*$I$3*$F$12 -> 398437.13 | J14: Profit per Food | K14: 6 | L14: =0.25*Table3[[#Totals],[Monthly Food Sales]] -> 1992.2917 | M14: =L14*K14 -> 11953.75
C15: Remaining Ticket Purchases (No F&B): | F15: =(1-F13)*$I$3*'Monthly Profit & Refined Data'!$C$8 -> 64222.619 | L15: Total: | M15: =SUM(M12:M14) -> 61249.118
B19: 3. Resolving Food Quality as an Issue Resulting in Boosted Sales for Cinema Customers **Assumption is Once Food Quality Issues are Resolved, Purchase Rate Doubles Potentially** | I19: 4. Quality and Operational Controls **Training Employees to be Efficient & Reducing Employee Expense** **Assumption is 7.5% increase in Yearly Profit**
C23: New Purchase Rate of Food: | E23: 0.25 | K23: Expected Savings in Operational Efficiency: | M23: 0.075
C24: Total Volume of Food Sales | E24: =E23*I3 -> 12844.524 | L24: Estimated Total Savings: | M24: =M23*C2 -> 37641.521
C25: Total Food Profit: | E25: =E24*'Monthly Profit & Refined Data'!F8 -> 77067.143
